{
  "main": {
    "name": "Hi, It's Saad Sohail",
    "description": "I am a Software Engineer & web development engineer and I use Node Js, React, Next Js to develop pages. This is my resume that can be used as the project home page or resume page",
    "image": "profilePic.jpg",
    "bio": "I'm Saad Sohail and I am a Full Stack Developer for ITZ Solutions. I am an accomplished coder and programmer, and I enjoy using my skills to contribute to the exciting technological advances that happen every day at ITZ Solutions. I graduated from the National University of Modern Technologies in 2020 with a Bachelor's Degree in Software Engineering. While in university, I started my professional carrier with Pakeproperty.com 2018.",
    "contactmessage": "Please contact me through email, social media or maybe with contact number.",
    "email": "engr.saadsohail@gmail.com",
    "phone": "+92-303-5229779",
    "github": "https://github.com/rishat5081",
    "address": {
      "city": "Islamabad",
      "province": "Federal",
      "zip": "46000"
    },
    "website": "http://www.timbakerdev.com",
    "resumedownload": "https://drive.google.com/file/d/1cpQVX5Zx_NNLXvsMwWhqzrRXHnAn2StX/view?usp=sharing",
    "social": [
      {
        "name": "facebook",
        "url": "https://www.facebook.com/rishat.5081/",
        "className": "fa fa-facebook"
      },
      {
        "name": "twitter",
        "url": "https://twitter.com/Saad5081",
        "className": "fa fa-twitter"
      },
      {
        "name": "linkedin",
        "url": "https://www.linkedin.com/in/saad-sohail-aa135b172/",
        "className": "fa fa-linkedin"
      },
      {
        "name": "instagram",
        "url": "https://www.instagram.com/hydrogen._.oxide/",
        "className": "fa fa-instagram"
      },
      {
        "name": "github",
        "url": "https://github.com/rishat5081",
        "className": "fa fa-github"
      }
    ]
  },
  "resume": {
    "skillmessage": "My skill's strength on the following technologies",
    "education": [
      {
        "school": "National University of Modern Technologies (NUML, Islamabad)",
        "degree": "Bachelor's Degree in Software Engineering",
        "graduated": "June 2020"
      },
      {
        "school": "Punjab Groups of College",
        "degree": "Fsc Pre-Engineering",
        "graduated": "May 2015"
      },
      {
        "school": "The Educators",
        "degree": "Science",
        "graduated": "May 2013"
      }
    ],
    "work": [
      {
        "company": "Medway Solutions",
        "title": "JavaScript Full Stack Developer - Remote",
        "years": "July 2021 - Present",
        "description": "Developing front end of website."
      },
      {
        "company": "ITZ Solutions",
        "title": "JavaScript Full Stack Developer",
        "years": "Sep 2018 - Present",
        "description": "Developing front end and back end of website, Create servers and databases, Designing and developing RESTful APIs"
      },
      {
        "company": "Pak e Property",
        "title": "Internee Android Developer",
        "years": "Aug 2018 - Sep 2018",
        "description": "Design and build applications for the Android platform, Work with APIs, Work on bug fixing and improving application performance"
      }
    ],
    "skills": [
      {
        "name": "Node Js",
        "level": "90%"
      },
      {
        "name": "ReactJs",
        "level": "80%"
      },
      {
        "name": "HTML",
        "level": "80%"
      },
      {
        "name": "CSS",
        "level": "90%"
      },
      {
        "name": "JavaScript",
        "level": "90%"
      },
      {
        "name": "UML Diagrams",
        "level": "95%"
      },
      {
        "name": "JAVA",
        "level": "50%"
      }
    ]
  }
}
